{
    "content_item_id": "5082e470-5b54-11e5-bc99-902b34691136",
    "name": "more sourly",
    "value": "more sourly",
    "order": 5,
    "order_locked": 0,
    "feedback": null,
    "score": 0,
    "content_comparison_type_id": null,
    "graph_line_id": null,
    "max_x": null,
    "max_y": null,
    "min_x": null,
    "min_y": null,
    "dropdown_id": null,
    "evaluate_user_response": 0,
    "uuid": "50d6ff28-5b54-11e5-bc99-902b34691136",
    "created_at": "2015-09-08 15:02:49",
    "updated_at": "2015-09-15 02:51:18"
}