{
    "content_item_id": "92a7bf41-2fcb-11e5-8ef8-22000ad80e72",
    "name": "If there are any of Earth\u2019s primordial rocks left in their original state, they have not yet been found.",
    "value": "If there are any of Earth\u2019s primordial rocks left in their original state, they have not yet been found.",
    "order": 5,
    "order_locked": 0,
    "feedback": null,
    "score": 0,
    "content_comparison_type_id": null,
    "graph_line_id": null,
    "max_x": null,
    "max_y": null,
    "min_x": null,
    "min_y": null,
    "dropdown_id": null,
    "evaluate_user_response": 0,
    "uuid": "92b408ac-2fcb-11e5-8ef8-22000ad80e72",
    "created_at": "2015-07-21 17:11:49",
    "updated_at": "2015-07-21 17:11:49"
}