{
    "content_item_id": "bafdbc47-8182-11e5-bc99-902b34691136",
    "name": "\u201cWish I\u2019d listened to mamma.\u201d",
    "value": "\u201cWish I\u2019d listened to mamma.\u201d",
    "order": 6,
    "order_locked": 0,
    "feedback": null,
    "score": 0,
    "content_comparison_type_id": null,
    "graph_line_id": null,
    "max_x": null,
    "max_y": null,
    "min_x": null,
    "min_y": null,
    "dropdown_id": null,
    "evaluate_user_response": 0,
    "uuid": "bb31a5b2-8182-11e5-bc99-902b34691136",
    "created_at": "2015-09-02 17:04:47",
    "updated_at": "2015-11-02 17:12:21"
}