{
    "content_item_id": "fdcd29a2-d17e-11e4-b41a-902b34691136",
    "name": "wearing sunglasses protects the eyes against ultraviolet rays",
    "value": "wearing sunglasses protects the eyes against ultraviolet rays",
    "order": "5",
    "order_locked": 0,
    "feedback": null,
    "score": 0,
    "content_comparison_type_id": null,
    "graph_line_id": null,
    "max_x": null,
    "max_y": null,
    "min_x": null,
    "min_y": null,
    "dropdown_id": null,
    "evaluate_user_response": 0,
    "uuid": "fdf5e040-d17e-11e4-b41a-902b34691136",
    "created_at": "2015-02-09 16:00:01",
    "updated_at": "2015-03-25 22:07:05"
}