{
    "content_passage_id": "98c950cd-3071-11e5-8ef8-22000ad80e72",
    "page_number": 1,
    "section_number": null,
    "order": 1,
    "contents": "(6) Rip currents form as incoming waves create an underwater sandbar close to shore (#1 diagram), and the waves push more and more water in between the sandbar and the shore (#2) until a section of this sandbar collapses and the water rushes back toward the sea (#3) through a narrow gap. (7) Once the flowing water passes through the narrow gap, it begins to spread out (#4). (8) It is here where the velocity and strength of the rip current circulation begins to weaken considerably.",
    "uuid": "67128f39-c39a-11e5-b42c-22000af4874e",
    "translation_id": null,
    "created_at": "2015-08-04 12:06:12",
    "updated_at": "2016-10-05 22:23:37"
}