{
    "content_passage_id": "765a2ba6-9404-11e6-babe-a89802414180",
    "page_number": 1,
    "section_number": null,
    "order": 1,
    "contents": "En la punta del tallo de una planta hay c\u00e9lulas indiferenciadas (madres) llamadas c\u00e9lulas meristem\u00e1ticas que permiten que la planta crezca. Como parte de un proyecto de investigaci\u00f3n, un cient\u00edfico recolect\u00f3 los siguientes datos sobre el tama\u00f1o de las c\u00e9lulas meristem\u00e1ticas en una especie de planta.",
    "uuid": "79feef1c-9404-11e6-babe-a89802414180",
    "translation_id": "44c2d844-9405-11e6-babe-a89802414180",
    "created_at": "0000-00-00 00:00:00",
    "updated_at": "2016-10-17 07:56:02"
}