{
    "content_passage_id": "765b1ed0-9404-11e6-babe-a89802414180",
    "page_number": 1,
    "section_number": null,
    "order": 1,
    "contents": "Entiendo que _____(13)_____ un inconveniente. Av\u00edsenme si hay algo que pueda hacer por ustedes. Si necesitan una estufa, vayan a la oficina. Tenemos varias estufas disponibles para prestarles a los residentes. Afortunadamente, el pron\u00f3stico del tiempo _____(14)_____ no se esperan temperaturas por debajo de los 50 grados.",
    "uuid": "7a024f9a-9404-11e6-babe-a89802414180",
    "translation_id": "44c2d844-9405-11e6-babe-a89802414180",
    "created_at": "0000-00-00 00:00:00",
    "updated_at": "2016-10-17 07:56:02"
}