{
    "content_passage_id": "9a14acc0-d182-11e4-8a55-123139092536",
    "page_number": 2,
    "section_number": null,
    "order": 2,
    "contents": "In stark contrast to this, college athletes are not paid. They are required to miss classes frequently due to travel. Many other restrictions are placed on college athletes. For example, any outside business ventures are greatly limited, and many restrictions are placed on their use of social media.",
    "uuid": "670b0a90-c39a-11e5-b42c-22000af4874e",
    "translation_id": null,
    "created_at": "2015-05-13 03:24:13",
    "updated_at": "2016-10-05 22:23:37"
}