{
    "content_passage_id": "9a14acc0-d182-11e4-8a55-123139092536",
    "page_number": 2,
    "section_number": null,
    "order": 2,
    "contents": "Much of this revenue from college sports is passed along to NCAA coaches, athletic directors, and executives who earn disproportionately high annual salaries. Many NCAA coaches routinely earn well over $1 million annually, while in most states, the highest paid public employees are basketball and football coaches.",
    "uuid": "670b08d2-c39a-11e5-b42c-22000af4874e",
    "translation_id": null,
    "created_at": "2015-05-13 03:24:13",
    "updated_at": "2016-10-05 22:23:37"
}