{
    "content_passage_id": "139e6248-b3ea-11e5-b42c-22000af4874e",
    "page_number": 2,
    "section_number": null,
    "order": 2,
    "contents": "State governments across the U.S. have succumbed to using casinos and lotteries as a way to infuse money into local economies. The trend is disturbing. Instead of properly using well-regulated spending and raising money through balanced taxation, governments are using a method that bleeds money from the poor and middle-class to fund the economy. Gambling is a dangerous way to raise money, and it should remain illegal.",
    "uuid": "67155f20-c39a-11e5-b42c-22000af4874e",
    "translation_id": null,
    "created_at": "2016-01-07 05:57:40",
    "updated_at": "2016-10-05 22:23:37"
}