{
    "uuid": "68b2acd0-9404-11e6-babe-a89802414180",
    "content_response_id": "eeb79c7f-65e7-11e4-b4ef-123139092536",
    "translation_id": "d03a3b3c-8b0f-11e6-babe-a89802414180",
    "name": " Se debe cuidar mucho a los ni\u00f1os peque\u00f1os mientras se encuentren cerca de las piscinas.",
    "value": " Se debe cuidar mucho a los ni\u00f1os peque\u00f1os mientras se encuentren cerca de las piscinas.",
    "feedback": null,
    "created_at": "0000-00-00 00:00:00",
    "updated_at": "2016-10-17 07:55:33",
    "deleted_at": null
}