{
    "uuid": "68b21cca-9404-11e6-babe-a89802414180",
    "content_response_id": "fd358530-65e7-11e4-b4ef-123139092536",
    "translation_id": "d03a3b3c-8b0f-11e6-babe-a89802414180",
    "name": "\"El ahogamiento por inmersi\u00f3n es la primera causa de muerte accidental entre ni\u00f1os de 1 a 4\u00a0a\u00f1os de edad y es la segunda causa de muerte en ni\u00f1os de 5 a 14\u00a0a\u00f1os de edad.\"",
    "value": "\"El ahogamiento por inmersi\u00f3n es la primera causa de muerte accidental entre ni\u00f1os de 1 a 4\u00a0a\u00f1os de edad y es la segunda causa de muerte en ni\u00f1os de 5 a 14\u00a0a\u00f1os de edad.\"",
    "feedback": null,
    "created_at": "0000-00-00 00:00:00",
    "updated_at": "2016-10-17 07:55:33",
    "deleted_at": null
}