{
    "metadata_type_id": "0a0fbb02-75a4-11e4-b41a-902b34691136",
    "parent_metadata_value_id": null,
    "code": "5.MD.5b",
    "description": "Apply the formulas V = l \u00d7 w \u00d7 h and V = b \u00d7 h for rectangular prisms to find volumes of right rectangular prisms with whole-number edge lengths in the context of solving real world and mathematical problems.",
    "subject_area_id": null,
    "uuid": "b6631fb2-f818-11e4-a7b8-902b34691136",
    "created_at": "2015-05-11 22:59:30",
    "updated_at": "2015-05-11 22:59:30",
    "hidden": "0"
}