{
    "product_id": "19e2f3cf-c9c4-11e4-b41a-902b34691136",
    "content_item_id": "3de7ade5-d182-11e4-8a55-123139092536",
    "title": "Language Practice Test 1",
    "intro_text": "<h1>Language<\/h1>\r\n<p>Welcome to the Language Initial Practice Test!<\/p>\r\n<p>This is a quick test to see how prepared you are for the language portion of the GED<sup>\u00ae<\/sup> Reasoning Through Language Arts test. We'll use your results to help create your learning plan and make recommendations as you move through the course.<\/p>\r\n<p>Take your time with this test. If you don't know how to answer a question, leave it blank and go on to the next question. Guessing is a good idea on the GED<sup>\u00ae<\/sup> test, but for this test, we really want to understand what you know. If you are unsure of an answer and want to think about it, you can click \u201cReview Question Later\u201d to come back to the question later.<\/p>\r\n<p>There are 15 questions on the test. These questions will give you practice with the types of questions you will see on the GED<sup>\u00ae<\/sup> test and help us generate a study plan for what you need to brush up on for the test.<\/p>\r\n<p>Relax and do your best!<\/p>",
    "uuid": "686e875f-c39a-11e5-b42c-22000af4874e",
    "created_at": "0000-00-00 00:00:00",
    "updated_at": "2016-01-25 11:32:45"
}