{
    "content_item_id": "664210da-c39a-11e5-b42c-22000af4874e",
    "address": "m=punctuation-quotes_underlines_italics.swf&s=writing&d=0&id=45a528c79f0014efdf9316a9481011ff&nav=I1,P1,P2,P3,P4,P5,P6,P7,P8,P9,P10,P11,P12,P13,P14",
    "width": null,
    "height": null,
    "autoplay": 0,
    "alt": null,
    "content_media_type_id": 3,
    "header_text": null,
    "caption_text": null,
    "uuid": "66b16e16-c39a-11e5-b42c-22000af4874e",
    "deleted": 0,
    "created_at": "2015-01-28 15:31:50",
    "updated_at": "2016-01-25 11:32:42"
}