{
    "content_item_id": "374e8a0e-d182-11e4-8a55-123139092536",
    "name": "September 11th brought the threat of terrorism to the forefront.",
    "value": "September 11th brought the threat of terrorism to the forefront.",
    "order": "5",
    "order_locked": 0,
    "feedback": null,
    "score": 0,
    "content_comparison_type_id": null,
    "graph_line_id": null,
    "max_x": null,
    "max_y": null,
    "min_x": null,
    "min_y": null,
    "dropdown_id": null,
    "evaluate_user_response": 0,
    "uuid": "376a1793-d182-11e4-8a55-123139092536",
    "created_at": "2015-03-03 18:42:37",
    "updated_at": "2015-03-25 21:51:57"
}