{
    "content_item_id": "665ba60f-c39a-11e5-b42c-22000af4874e",
    "name": "In very low temperatures, wait for electronic equipment to return again to normal room temperature from being nearly frozen before restarting the equipment.",
    "value": "In very low temperatures, wait for electronic equipment to return again to normal room temperature from being nearly frozen before restarting the equipment.",
    "order": 5,
    "order_locked": 0,
    "feedback": null,
    "score": 0,
    "content_comparison_type_id": null,
    "graph_line_id": null,
    "max_x": null,
    "max_y": null,
    "min_x": null,
    "min_y": null,
    "dropdown_id": null,
    "evaluate_user_response": 0,
    "uuid": "67528fc0-c39a-11e5-b42c-22000af4874e",
    "created_at": "2015-08-12 21:44:42",
    "updated_at": "2016-01-25 11:32:43"
}