{
    "content_item_id": "75812ce1-8182-11e5-bc99-902b34691136",
    "name": "because early archaeologists lied about their findings",
    "value": "because early archaeologists lied about their findings",
    "order": 6,
    "order_locked": 0,
    "feedback": null,
    "score": 0,
    "content_comparison_type_id": null,
    "graph_line_id": null,
    "max_x": null,
    "max_y": null,
    "min_x": null,
    "min_y": null,
    "dropdown_id": null,
    "evaluate_user_response": 0,
    "uuid": "75b71dd4-8182-11e5-bc99-902b34691136",
    "created_at": "2015-08-26 14:52:34",
    "updated_at": "2015-11-02 17:10:50"
}