{
    "content_item_id": "a16c2fb3-a025-11e4-b41a-902b34691136",
    "name": "drought",
    "value": "drought",
    "order": "5",
    "order_locked": 0,
    "feedback": null,
    "score": 0,
    "content_comparison_type_id": null,
    "graph_line_id": null,
    "max_x": null,
    "max_y": null,
    "min_x": null,
    "min_y": null,
    "dropdown_id": null,
    "evaluate_user_response": 0,
    "uuid": "a194e6c4-a025-11e4-b41a-902b34691136",
    "created_at": "0000-00-00 00:00:00",
    "updated_at": "2015-03-25 21:50:58"
}